Metadata-Version: 1.0
Name: uwuifier
Version: 0.1.0
Summary: because I should not code tired
Home-page: UNKNOWN
Author: Nathan Tucker
Author-email: UNKNOWN
License: MIT
Platform: UNKNOWN
